Metadata-Version: 1.0
Name: uvhttp
Version: 1.18
Summary: High performance Python HTTP client
Home-page: https://github.com/justinbarrick/uvhttp
Author: UNKNOWN
Author-email: UNKNOWN
License: UNKNOWN
Platform: UNKNOWN
